uuvmissionsim/__init__.py
uuvmissionsim/config.py
uuvmissionsim/path.py
uuvmissionsim/regrid_roms.py
uuvmissionsim/simulator.py
uuvmissionsim/sensors/__init__.py
uuvmissionsim/sensors/adcp.py
uuvmissionsim/sensors/ctd.py
uuvmissionsim/utilities/__init__.py
uuvmissionsim/utilities/path_utils.py
uuvmissionsim/utilities/regrid_roms_utils.py
uuvmissionsim/utilities/sensor_noise.py
uuvmissionsim/utilities/sensor_utils.py
uuv_mission_simulator-0.1.0.dist-info/METADATA
uuv_mission_simulator-0.1.0.dist-info/WHEEL
uuv_mission_simulator-0.1.0.dist-info/top_level.txt
uuv_mission_simulator-0.1.0.dist-info/RECORD
